idom_router/__init__.py
idom_router/bundle.js
idom_router/router.py
idom_router-0.0.1.dist-info/LICENSE
idom_router-0.0.1.dist-info/METADATA
idom_router-0.0.1.dist-info/WHEEL
idom_router-0.0.1.dist-info/top_level.txt
idom_router-0.0.1.dist-info/RECORD
