Metadata-Version: 2.1
Name: idom-router
Version: 0.0.1
Summary: A URL router for IDOM
Home-page: https://github.com/idom-team/idom-router
Author: Ryan Morshead
Author-email: ryan.morshead@gmail.com
Keywords: idom,components
Platform: Linux
Platform: Mac OS X
Platform: Windows
Classifier: Environment :: Web Environment
Classifier: Intended Audience :: Developers
Classifier: Intended Audience :: Science/Research
Classifier: Programming Language :: Python :: 3.7
Classifier: Programming Language :: Python :: 3.8
Classifier: Programming Language :: Python :: 3.9
Classifier: Topic :: Software Development :: User Interfaces
Classifier: Topic :: Software Development :: Widget Sets
Classifier: Typing :: Typed
Requires-Python: >=3.7
License-File: LICENSE
Requires-Dist: idom (>=0.39.0)
